{
    "name": "AccessToken",
    "fields": [
        {
            "fieldName": "nsrmc",
            "javadoc": "纳税人名称",
            "fieldType": "String",
            "fieldValidateRules": [
                "maxlength"
            ],
            "fieldValidateRulesMaxlength": 20
        },
        {
            "fieldName": "nsrsbh",
            "javadoc": "纳税人识别号",
            "fieldType": "String",
            "fieldValidateRules": [
                "required",
                "maxlength"
            ],
            "fieldValidateRulesMaxlength": 30
        },
        {
            "fieldName": "expires",
            "javadoc": "超时时间秒",
            "fieldType": "String",
            "fieldValidateRules": [
                "maxlength"
            ],
            "fieldValidateRulesMaxlength": 8
        },
        {
            "fieldName": "pkey",
            "javadoc": "请求密钥",
            "fieldType": "String",
            "fieldValidateRules": [
                "required",
                "maxlength"
            ],
            "fieldValidateRulesMaxlength": 40
        },
        {
            "fieldName": "createTime",
            "javadoc": "创建时间",
            "fieldType": "Instant"
        },
        {
            "fieldName": "updateTime",
            "javadoc": "更新时间",
            "fieldType": "Instant"
        }
    ],
    "relationships": [],
    "changelogDate": "20180714043356",
    "javadoc": "系统签到获取Token",
    "entityTableName": "access_token",
    "dto": "no",
    "pagination": "no",
    "service": "no",
    "jpaMetamodelFiltering": false,
    "fluentMethods": true,
    "clientRootFolder": "",
    "applications": "*"
}